trism/__init__.py
trism/client.py
trism/meta.py
trism/model.py
trism/types.py
trism-0.0.1.post1.dist-info/LICENSE
trism-0.0.1.post1.dist-info/METADATA
trism-0.0.1.post1.dist-info/WHEEL
trism-0.0.1.post1.dist-info/top_level.txt
trism-0.0.1.post1.dist-info/zip-safe
trism-0.0.1.post1.dist-info/RECORD
