Metadata-Version: 2.1
Name: trism
Version: 0.0.1.post1
Summary: Inference with Triton Inference Server easily.
Home-page: https://github.com/hieupth/trismid
Author: Hieu Pham
Author-email: 64821726+hieupth@users.noreply.github.com
License: GNU AGPL v3.0
Classifier: Intended Audience :: Developers
Classifier: Topic :: Software Development :: Build Tools
License-File: LICENSE
Requires-Dist: pinecore
